ZhihuWendaRuheKandaiIbmCaijian40SuiYishangYuangongPinyongNianqingYuangongMubiaoShiShixianChuangxin/README.md
ZhihuWendaRuheKandaiIbmCaijian40SuiYishangYuangongPinyongNianqingYuangongMubiaoShiShixianChuangxin/__init__.py
ZhihuWendaRuheKandaiIbmCaijian40SuiYishangYuangongPinyongNianqingYuangongMubiaoShiShixianChuangxin/__main__.py
ZhihuWendaRuheKandaiIbmCaijian40SuiYishangYuangongPinyongNianqingYuangongMubiaoShiShixianChuangxin/file.epub
ZhihuWendaRuheKandaiIbmCaijian40SuiYishangYuangongPinyongNianqingYuangongMubiaoShiShixianChuangxin/index.html
ZhihuWendaRuheKandaiIbmCaijian40SuiYishangYuangongPinyongNianqingYuangongMubiaoShiShixianChuangxin/css/__init__.py
ZhihuWendaRuheKandaiIbmCaijian40SuiYishangYuangongPinyongNianqingYuangongMubiaoShiShixianChuangxin/css/annotations.css
ZhihuWendaRuheKandaiIbmCaijian40SuiYishangYuangongPinyongNianqingYuangongMubiaoShiShixianChuangxin/css/main.css
ZhihuWendaRuheKandaiIbmCaijian40SuiYishangYuangongPinyongNianqingYuangongMubiaoShiShixianChuangxin/css/normalize.css
ZhihuWendaRuheKandaiIbmCaijian40SuiYishangYuangongPinyongNianqingYuangongMubiaoShiShixianChuangxin/css/popup.css
ZhihuWendaRuheKandaiIbmCaijian40SuiYishangYuangongPinyongNianqingYuangongMubiaoShiShixianChuangxin/font/__init__.py
ZhihuWendaRuheKandaiIbmCaijian40SuiYishangYuangongPinyongNianqingYuangongMubiaoShiShixianChuangxin/font/fontello.eot
ZhihuWendaRuheKandaiIbmCaijian40SuiYishangYuangongPinyongNianqingYuangongMubiaoShiShixianChuangxin/font/fontello.svg
ZhihuWendaRuheKandaiIbmCaijian40SuiYishangYuangongPinyongNianqingYuangongMubiaoShiShixianChuangxin/font/fontello.ttf
ZhihuWendaRuheKandaiIbmCaijian40SuiYishangYuangongPinyongNianqingYuangongMubiaoShiShixianChuangxin/font/fontello.woff
ZhihuWendaRuheKandaiIbmCaijian40SuiYishangYuangongPinyongNianqingYuangongMubiaoShiShixianChuangxin/img/__init__.py
ZhihuWendaRuheKandaiIbmCaijian40SuiYishangYuangongPinyongNianqingYuangongMubiaoShiShixianChuangxin/img/annotator-glyph-sprite.png
zhihu_wenda_ruhe_kandai_ibm_caijian_40_sui_yishang_yuangong_pinyong_nianqing_yuangong_mubiao_shi_shixian_chuangxin-2024.3.5.0.dist-info/METADATA
zhihu_wenda_ruhe_kandai_ibm_caijian_40_sui_yishang_yuangong_pinyong_nianqing_yuangong_mubiao_shi_shixian_chuangxin-2024.3.5.0.dist-info/WHEEL
zhihu_wenda_ruhe_kandai_ibm_caijian_40_sui_yishang_yuangong_pinyong_nianqing_yuangong_mubiao_shi_shixian_chuangxin-2024.3.5.0.dist-info/entry_points.txt
zhihu_wenda_ruhe_kandai_ibm_caijian_40_sui_yishang_yuangong_pinyong_nianqing_yuangong_mubiao_shi_shixian_chuangxin-2024.3.5.0.dist-info/top_level.txt
zhihu_wenda_ruhe_kandai_ibm_caijian_40_sui_yishang_yuangong_pinyong_nianqing_yuangong_mubiao_shi_shixian_chuangxin-2024.3.5.0.dist-info/RECORD
