Metadata-Version: 2.1
Name: zhihu-wenda-ruhe-kandai-ibm-caijian-40-sui-yishang-yuangong-pinyong-nianqing-yuangong-mubiao-shi-shixian-chuangxin
Version: 2024.3.5.0
Summary: 知乎问答：如何看待 IBM 裁减 40 岁以上员工，聘用年轻员工，目标是实现创新？
Home-page: https://github.com/apachecn/zhihu-wenda-ruhe-kandai-ibm-caijian-40-sui-yishang-yuangong-pinyong-nianqing-yuangong-mubiao-shi-shixian-chuangxin
Author: ApacheCN
Author-email: apachecn@163.com
Classifier: Development Status :: 4 - Beta
Classifier: Environment :: Console
Classifier: Intended Audience :: Developers
Classifier: Intended Audience :: End Users/Desktop
Classifier: License :: Other/Proprietary License
Classifier: Natural Language :: Chinese (Simplified)
Classifier: Natural Language :: English
Classifier: Operating System :: OS Independent
Classifier: Programming Language :: Python :: 3
Classifier: Programming Language :: Python :: 3 :: Only
Classifier: Programming Language :: Python :: 3.6
Classifier: Programming Language :: Python :: 3.7
Classifier: Topic :: Text Processing :: Markup :: Markdown
Classifier: Topic :: Text Processing :: Markup :: HTML
Classifier: Topic :: Internet :: WWW/HTTP
Classifier: Topic :: Software Development :: Documentation
Classifier: Topic :: Documentation
Requires-Python: >=3.6
